speedups/__about__.py
speedups/__init__.py
speedups/hton.h
speedups/hton.pxd
speedups/psycopg_array.c
speedups/psycopg_array.cp312-win_amd64.pyd
speedups/psycopg_array.pyi
speedups/psycopg_array.pyx
speedups/psycopg_loaders.py
speedups/py.typed
speedups-1.4.0.dist-info/METADATA
speedups-1.4.0.dist-info/WHEEL
speedups-1.4.0.dist-info/top_level.txt
speedups-1.4.0.dist-info/RECORD
