Metadata-Version: 2.1
Name: speedups
Version: 1.4.0
Summary: Library with some C and Cython code for speeding up common operations. This is externalized to avoid the hassle of building binary wheels in my other projects.
Home-page: https://github.com/WoLpH/speedups/
Author: Rick van Hattem, Joren Hammudoglu
Author-email: Wolph@Wol.ph, jhammudoglu@gmail.com
License: BSD 3-Clause License
Keywords: Cython,C,C++,speedups,Numpy,PostgreSQL,PsycoPG
Requires-Python: >=3.8
Requires-Dist: numpy >=1.23.5
Provides-Extra: postgres
Requires-Dist: psycopg >=3.0.8 ; extra == 'postgres'
Provides-Extra: tests
Requires-Dist: psycopg[binary] >=3.0.8 ; extra == 'tests'
Requires-Dist: pytest >=8.0.1 ; extra == 'tests'
Requires-Dist: pytest-postgresql >=5.1.0 ; extra == 'tests'
